LICENSE.txt
MANIFEST.in
README.md
setup.py
jk_php_version_parser/ComposerToken.py
jk_php_version_parser/ComposerTokenStream.py
jk_php_version_parser/ComposerVersionParser.py
jk_php_version_parser/ComposerVersionTokenizer.py
jk_php_version_parser/ImplementationErrorException.py
jk_php_version_parser/_ComposerTokenPattern.py
jk_php_version_parser/_ComposerTokenPatternSequence.py
jk_php_version_parser/__init__.py
jk_php_version_parser.egg-info/PKG-INFO
jk_php_version_parser.egg-info/SOURCES.txt
jk_php_version_parser.egg-info/dependency_links.txt
jk_php_version_parser.egg-info/not-zip-safe
jk_php_version_parser.egg-info/requires.txt
jk_php_version_parser.egg-info/top_level.txt