Metadata-Version: 2.1
Name: jk-php-version-parser
Version: 0.2022.1.30
Summary: Parses PHP composer version constraints.
Home-page: UNKNOWN
Author: Jürgen Knauth
Author-email: pubsrc@binary-overflow.de
License: proprietary
Keywords: php,parser,version,constraints,composer
Platform: UNKNOWN
Classifier: Development Status :: 3 - Alpha
Classifier: Programming Language :: Python :: 3
